brat_widget/__init__.py
brat_widget/_version.py
brat_widget/annotation.py
brat_widget/brat-widget-0.2.5.tgz
brat_widget/common.py
brat_widget/configuration.py
brat_widget/document.py
brat_widget/document_test.py
brat_widget/messager.py
brat_widget/verify_annotations.py
brat_widget/widget.py
brat_widget/static/3b826fc6b1952a6124edd1ff72b8570b.png
brat_widget/static/4095446dc53cb3cddd200b519c39245d.png
brat_widget/static/4c1946a09d9ffdf7aa53eec472488383.png
brat_widget/static/60c9228e454c6d03662194eaca4f88b3.png
brat_widget/static/671308f1e6a219fb111829d6ea0de445.gif
brat_widget/static/6e9414f6748c0120a9d738cf28a82aa3.png
brat_widget/static/7819367ee0e97e6717abf71830872813.png
brat_widget/static/838cb1eedd8fa64c941fc3a49fd0cc82.png
brat_widget/static/8aa7982c6a44ad005cc4aacd27f0e856.png
brat_widget/static/a51c5608d01acf32df728f299767f82b.gif
brat_widget/static/b233dbc966fbe5e78604bcd1ae562249.png
brat_widget/static/bfc519b33182a98b06ec691b38dde7c0.png
brat_widget/static/c3a9edbc7ca7239283c744d16a996999.gif
brat_widget/static/c3d0bd2b2097e36ae15a410f997d2715.png
brat_widget/static/cf1f86465e077f9676e65fbe1fa9194a.png
brat_widget/static/extension.js
brat_widget/static/index.js
brat_widget/static/index.js.map
brat_widget/static/jupyterlab-plugin.js
brat_widget/static/jupyterlab-plugin.js.map
brat_widget/static/package.json
brat_widget/static/static/fonts/Astloch-Bold.ttf
brat_widget/static/static/fonts/Liberation_Sans-Regular.svg
brat_widget/static/static/fonts/Liberation_Sans-Regular.ttf
brat_widget/static/static/fonts/PT_Sans-Caption-Web-Regular.svg
brat_widget/static/static/fonts/PT_Sans-Caption-Web-Regular.ttf
brat_widget-0.2.5.data/data/etc/jupyter/nbconfig/notebook.d/brat-widget.json
brat_widget-0.2.5.data/data/share/jupyter/lab/extensions/brat-widget-0.2.5.tgz
brat_widget-0.2.5.data/data/share/jupyter/nbextensions/brat-widget/Astloch-Bold.ttf
brat_widget-0.2.5.data/data/share/jupyter/nbextensions/brat-widget/Liberation_Sans-Regular.svg
brat_widget-0.2.5.dist-info/LICENSE
brat_widget-0.2.5.dist-info/METADATA
brat_widget-0.2.5.dist-info/WHEEL
brat_widget-0.2.5.dist-info/top_level.txt
brat_widget-0.2.5.dist-info/RECORD
